{
  "title": "2023年12月 GESP C++ 5级",
  "category": "GESP",
  "level": "5",
  "date": "2023-12",
  "time_limit": 60,
  "total_score": 100,
  "description": "2023年12月 GESP C++ 5级认证考试真题（含编程操作题部分）",
  "questions": [
    {
      "type": "choice",
      "id": 1,
      "score": 2,
      "answer": "C",
      "options": [
        {
          "key": "A",
          "text": "`fiboA()` 用递归方式，`fiboB()` 循环方式"
        },
        {
          "key": "B",
          "text": "`fiboA()` 更加符合斐波那契数列的数学定义，直观易于理解，而 `fiboB()` 需要将数学定义转换为计算机程序实现"
        },
        {
          "key": "C",
          "text": "`fiboA()` 不仅仅更加符合数学定义，直观易于理解，且因代码量较少执行效率更高"
        },
        {
          "key": "D",
          "text": "`fiboB()` 虽然代码量有所增加，但其执行效率更高"
        }
      ],
      "content": "下面 C++ 代码用于求斐波那契数列，该数列第 $1$、$2$ 项为 $1$，以后各项均是前两项之和。下面有关说法错误的是( )。"
    },
    {
      "type": "choice",
      "id": 2,
      "score": 2,
      "answer": "C",
      "options": [
        {
          "key": "A",
          "text": "`mergeSort(SList, T2, s, m, len)`, `mergeSort(SList, T2, m, t, len)`"
        },
        {
          "key": "B",
          "text": "`mergeSort(SList, T2, s, m-1, len)`, `mergeSort(SList, T2, m+1, t, len)`"
        },
        {
          "key": "C",
          "text": "`mergeSort(SList, T2, s, m, len)`, `mergeSort(SList, T2, m+1, t, len)`"
        },
        {
          "key": "D",
          "text": "`mergeSort(SList, T2, s, m-1, len)`, `mergeSort(SList, T2, m-1, t, len)`"
        }
      ],
      "content": "下面 C++ 代码以递归方式实现合并排序，并假设 `merge(int T[], int R[], int s, int m, int t)` 函数将有序（同样排序规则）的 `T[s..m]` 和 `T[m+1..t]` 归并到 `R[s..t]` 中。横线处应填上代码是( )。"
    },
    {
      "type": "choice",
      "id": 3,
      "score": 2,
      "answer": "D",
      "options": [
        {
          "key": "A",
          "text": "1->120<===>2->120"
        },
        {
          "key": "B",
          "text": "1->120<===>1->120"
        },
        {
          "key": "C",
          "text": "1->120<===>1->2->3->4->5->120"
        },
        {
          "key": "D",
          "text": "1->120<===>2->3->4->5->6->120"
        }
      ],
      "content": "阅读下面的 C++ 代码，执行后其输出是( )。"
    },
    {
      "type": "choice",
      "id": 4,
      "score": 2,
      "answer": "A",
      "options": [
        {
          "key": "A",
          "text": "`!isEven(lstA[j]) && isEven(lstA[j+1])`"
        },
        {
          "key": "B",
          "text": "`isEven(lstA[j]) && !isEven(lstA[j+1])`"
        },
        {
          "key": "C",
          "text": "`lstA[j] > lstA[j+1]`"
        },
        {
          "key": "D",
          "text": "`lstA[j] < lstA[j+1]`"
        }
      ],
      "content": "下面的 C++ 用于对 `lstA` 排序，使得偶数在前奇数在后，横线处应填入( )。"
    },
    {
      "type": "choice",
      "id": 5,
      "score": 2,
      "answer": "B",
      "options": [
        {
          "key": "A",
          "text": "`if(pHead) {p->next = pHead->next, pHead->next->prev = p;}`"
        },
        {
          "key": "B",
          "text": "`if(pHead->next) {p->next = pHead->next, pHead->next->prev = p;}`"
        },
        {
          "key": "C",
          "text": "`p->next = pHead->next, pHead->next->prev = p;`"
        },
        {
          "key": "D",
          "text": "触发异常，不能对空指针进行操作。"
        }
      ],
      "content": "下面的 C++ 代码用于将字符串保存到带头节点的双向链表中，并对重复的串计数，然后将最新访问的串的节点放在链头便于查找。横线处应填入代码是（ ）。"
    },
    {
      "type": "choice",
      "id": 6,
      "score": 2,
      "answer": "A",
      "options": [
        {
          "key": "A",
          "text": "如果 $x$ 小于 $10$ ，`rc` 值也不会超过 $20$"
        },
        {
          "key": "B",
          "text": "`foo` 可能无限递归"
        },
        {
          "key": "C",
          "text": "`foo` 可以求出 $x$ 和 $y$ 的最大公共质因子"
        },
        {
          "key": "D",
          "text": "`foo` 能够求出 $x$ 和 $y$ 的最小公倍数"
        }
      ],
      "content": "有关下面 C++ 代码说法正确的是（ ）。\n"
    },
    {
      "type": "choice",
      "id": 7,
      "score": 2,
      "answer": "C",
      "options": [
        {
          "key": "A",
          "text": "`qSort(less) + qSort(greater) + (vector<int>)pivot`"
        },
        {
          "key": "B",
          "text": "`(vector<int>)pivot + (qSort(less) + qSort(greater))`"
        },
        {
          "key": "C",
          "text": "`(qSort(less) + (vector<int>)pivot + qSort(greater))`"
        },
        {
          "key": "D",
          "text": "`qSort(less) + pivot + qSort(greater)`"
        }
      ],
      "content": "下面的 C++ 代码实现对 `list` 的快速排序，有关说法，错误的是（ ）。"
    },
    {
      "type": "choice",
      "id": 8,
      "score": 2,
      "answer": "B",
      "options": [
        {
          "key": "A",
          "text": "`isPrimeA()` 的最坏时间复杂度是 $O(N)$ ，`isPrimeB()` 的最坏时间复杂度是 $O(\\sqrt{N})$ ，`isPrimeA()` 优于 `isPrimeB()`"
        },
        {
          "key": "B",
          "text": "`isPrimeA()` 的最坏时间复杂度是 $O(N)$ ，`isPrimeB()` 的最坏时间复杂度是 $O(\\sqrt{N})$ ，`isPrimeB()` 绝大多数情况下优于 `isPrimeA()`"
        },
        {
          "key": "C",
          "text": "`isPrimeA()` 的最坏时间复杂度是 $O(\\sqrt{N})$ ，`isPrimeB()` 的最坏时间复杂度是 $O(N)$ ，`isPrimeA()` 优于 `isPrimeB()`"
        },
        {
          "key": "D",
          "text": "`isPrimeA()` 的最坏时间复杂度是 $O(\\sqrt{N})$ ，`isPrimeB()` 的最坏时间复杂度是 $O(N)$ ，`isPrimeA()` 优于 `isPrimeB()`"
        }
      ],
      "content": "下面 C++ 代码中的 `isPrimeA()` 和 `isPrimeB()` 都用于判断参数 $N$ 是否素数，有关其时间复杂度的正确说法是（ ）。"
    },
    {
      "type": "choice",
      "id": 9,
      "score": 2,
      "answer": "D",
      "options": [
        {
          "key": "A",
          "text": "代码采用二分法实现有序 `list` 的查找"
        },
        {
          "key": "B",
          "text": "代码采用分治算法实现有序 `list` 的查找"
        },
        {
          "key": "C",
          "text": "代码采用递归方式实现有序 `list` 的查找"
        },
        {
          "key": "D",
          "text": "代码采用动态规划算法实现有序 `list` 的查找"
        }
      ],
      "content": "下面 C++ 代码用于有序 `list` 的二分查找，有关说法错误的是（ ）。"
    },
    {
      "type": "choice",
      "id": 10,
      "score": 2,
      "answer": "B",
      "options": [
        {
          "key": "A",
          "text": ""
        },
        {
          "key": "B",
          "text": ""
        },
        {
          "key": "C",
          "text": ""
        },
        {
          "key": "D",
          "text": ""
        }
      ],
      "content": "在上题的 `_binarySearch` 算法中，如果 `lst` 中有 $N$ 个元素，其时间复杂度是（ ）。"
    },
    {
      "type": "choice",
      "id": 11,
      "score": 2,
      "answer": "D",
      "options": [
        {
          "key": "A",
          "text": "`c.push_back(t % 10)`, `t = t % 10`;"
        },
        {
          "key": "B",
          "text": "`c.push_back(t / 10)`, `t = t % 10`;"
        },
        {
          "key": "C",
          "text": "`c.push_back(t / 10)`, `t = t / 10`;"
        },
        {
          "key": "D",
          "text": "`c.push_back(t % 10)`, `t = t / 10`;"
        }
      ],
      "content": "下面的 C++ 代码使用数组模拟整数加法，可以处理超出大整数范围的加法运算。横线处应填入代码是（ ）。"
    },
    {
      "type": "choice",
      "id": 12,
      "score": 2,
      "answer": "B",
      "options": [
        {
          "key": "A",
          "text": "上述代码构成单向链表"
        },
        {
          "key": "B",
          "text": "上述代码构成双向链表"
        },
        {
          "key": "C",
          "text": "上述代码构成循环链表"
        },
        {
          "key": "D",
          "text": "上述代码构成指针链表"
        }
      ],
      "content": "有关下面 C++ 代码的说法正确的是（ ）。"
    },
    {
      "type": "choice",
      "id": 13,
      "score": 2,
      "answer": "B",
      "options": [
        {
          "key": "A",
          "text": "信息过滤"
        },
        {
          "key": "B",
          "text": "信号中继"
        },
        {
          "key": "C",
          "text": "避免攻击"
        },
        {
          "key": "D",
          "text": "数据加密"
        }
      ],
      "content": "通讯卫星在通信网络系统中主要起到（）的作用。"
    },
    {
      "type": "choice",
      "id": 14,
      "score": 2,
      "answer": "C",
      "options": [
        {
          "key": "A",
          "text": "埃氏筛法"
        },
        {
          "key": "B",
          "text": "线性筛法"
        },
        {
          "key": "C",
          "text": "二分答案"
        },
        {
          "key": "D",
          "text": "枚举法"
        }
      ],
      "content": "小杨想编写一个判断任意输入的整数 $N$ 是否为素数的程序，下面哪个方法不合适？（ ）"
    },
    {
      "type": "choice",
      "id": 15,
      "score": 2,
      "answer": "B",
      "options": [
        {
          "key": "A",
          "text": "选择排序"
        },
        {
          "key": "B",
          "text": "快速排序"
        },
        {
          "key": "C",
          "text": "堆排序"
        },
        {
          "key": "D",
          "text": "冒泡排序"
        }
      ],
      "content": "下面的排序算法都要处理多趟数据，哪种排序算法不能保证在下一趟处理时从待处理数据中选出最大或最小的数据？（ ）"
    },
    {
      "type": "judge",
      "id": 16,
      "score": 2,
      "answer": "True",
      "content": "归并排序的时间复杂度是 $O(n \\log n)$。( )"
    },
    {
      "type": "judge",
      "id": 17,
      "score": 2,
      "answer": "False",
      "content": "小杨在生日聚会时拿一块 $H \\times W$ 的巧克力招待来的 $K$ 个小朋友，保证每位小朋友至少能获得一块相同大小的巧克力。那么小杨想分出来最大边长的巧克力可以使用二分法。（ ）"
    },
    {
      "type": "judge",
      "id": 18,
      "score": 2,
      "answer": "True",
      "content": "以下 C++ 代码能以递归方式实现斐波那契数列，该数列第 1、2 项为 $1$，以后各项均是前两项之和。( )"
    },
    {
      "type": "judge",
      "id": 19,
      "score": 2,
      "answer": "False",
      "content": "贪心算法可以达到局部最优，但可能不是全局最优解。( )"
    },
    {
      "type": "judge",
      "id": 20,
      "score": 2,
      "answer": "True",
      "content": "小杨设计了一个拆数程序，它能够将任意的非质数自然数 $N$ 转换成若干个质数的乘积，这个程序是可以设计出来的。（ ）"
    },
    {
      "type": "judge",
      "id": 21,
      "score": 2,
      "answer": "True",
      "content": "插入排序有时比快速排序时间复杂度更低。（ ）"
    },
    {
      "type": "judge",
      "id": 22,
      "score": 2,
      "answer": "True",
      "content": "下面的 C++ 代码能实现十进制正整数 $N$ 转换为八进制并输出。（ ）"
    },
    {
      "type": "judge",
      "id": 23,
      "score": 2,
      "answer": "False",
      "content": "对数组 `int arr[] = {2, 6, 3, 5, 4, 8, 1, 0, 9, 10}` 执行 `sort(arr, arr+10)`，则执行后 `arr` 中的数据调整为 `{0, 1, 2, 3, 4, 5, 6, 8, 9, 10}`。（ ）"
    },
    {
      "type": "judge",
      "id": 24,
      "score": 2,
      "answer": "True",
      "content": "小杨想写一个程序来算出正整数 $N$ 有多少个因数，经过思考他写出了一个重复没有超过 $N/2$ 次的循环就能够算出来了。（ ）"
    },
    {
      "type": "judge",
      "id": 25,
      "score": 2,
      "answer": "True",
      "content": "同样的整数序列分别保存在单链表和双向链中，这两种链表上的简单冒泡排序的复杂度相同。（ ）"
    },
    {
      "type": "program",
      "id": 26,
      "score": 25,
      "answer": "None",
      "content": "**试题名称：小杨的幸运数**\n\n> 时间限制：1.0 s | 内存限制：512.0 MB\n\n**题目描述**\n\n小杨认为，所有大于等于 $a$ 的完全平方数都是他的超级幸运数。\n\n小杨还认为，所有超级幸运数的倍数都是他的幸运数。自然地，小杨的所有超级幸运数也都是幸运数。\n\n对于一个非幸运数，小杨规定，可以将它一直 $+1$，直到它变成一个幸运数。我们把这个过程叫做幸运化。例如，如果 $a=4$，那么 $4$ 是最小的幸运数，而 $1$ 不是，但我们可以连续对 $1$ 做 $3$ 次 $+1$ 操作，使其变为 $4$，所以我们可以说， $1$ 幸运化后的结果是 $4$。\n\n现在，小杨给出 $N$ 个数，请你首先判断它们是不是幸运数；接着，对于非幸运数，请你将它们幸运化。\n\n**输入格式**\n\n第一行 $2$ 个正整数 $a, N$。\n\n接下来 $N$ 行，每行一个正整数 $x$ ，表示需要判断（幸运化）的数。\n\n**输出格式**\n\n输出 $N$ 行，对于每个给定的 $x$ ，如果它是幸运数，请输出 `lucky`，否则请输出将其幸运化后的结果。\n\n**样例输入 #1**\n```\n2 4 \n1 \n4 \n5 \n9\n```\n\n**样例输出 #1**\n```\n4 \nlucky \n8 \nlucky\n```\n\n**样例输入 #2**\n```\n16 11 \n1 \n2 \n4 \n8 \n16 \n32 \n64 \n128 \n256 \n512\n1024\n```\n\n**样例输出 #2**\n```\n16 \n16 \n16 \n16 \nlucky \nlucky \nlucky \nlucky \nlucky \nlucky \nlucky\n```\n\n**说明/提示**\n\n**样例解释 1**\n\n$1$ 虽然是完全平方数，但它小于 $a$，因此它并不是超级幸运数，也不是幸运数。将其进行 $3$ 次 $+1$ 操作后，最终得到幸运数 $4$。\n\n$4$ 是幸运数，因此直接输出 `lucky`。\n\n$5$ 不是幸运数，将其进行 $3$ 次 $+1$ 操作后，最终得到幸运数 $8$。\n\n$9$ 是幸运数，因此直接输出 `lucky`。\n\n**数据规模**\n\n对于 $30\\%$ 的测试点，保证 $a,x \\le 100,N \\le 100$。\n\n对于 $60\\%$ 的测试点，保证 $a,x \\le 10^6$。\n\n对于所有测试点，保证 $a \\le 1,000,000$；保证 $N \\le 2 \\times 10^5$；保证 $1 \\le x \\le 1,000,001$。",
      "options": [],
      "section": "GESP 编程操作题"
    },
    {
      "type": "program",
      "id": 27,
      "score": 25,
      "answer": "None",
      "content": "**试题名称：烹饪问题**\n\n> 时间限制：1.0 s | 内存限制：512.0 MB\n\n**题目描述**\n\n有 $N$ 种食材，编号从 $1$ 至 $N$，其中第 $i$ 种食材的美味度为 $a_i$。\n\n不同食材之间的组合可能产生奇妙的化学反应。具体来说，如果两种食材的美味度分别为 $x$ 和 $y$ ，那么它们的契合度为 $x\\ \\text{and}\\ y $。\n\n其中，$\\text{and}$ 运算为按位与运算，需要先将两个运算数转换为二进制，然后在高位补足 ，再逐位进行与运算。例如，$12$ 与 $6$ 的二进制表示分别为 $1100$ 和 $0110$ ，将它们逐位进行与运算，得到 $0100$ ，转换为十进制得到 4，因此 $12\\ \\text{and}\\ 6 = 4$。**在 C++ 或 Python 中，可以直接使用 `&` 运算符表示与运算。**\n\n\n现在，请你找到契合度最高的两种食材，并输出它们的契合度。\n\n**输入格式**\n\n第一行一个整数 $N$，表示食材的种数。\n\n接下来一行 $N$ 个用空格隔开的整数，依次为 $a_1,\\cdots,a_N$，表示各种食材的美味度。\n\n**输出格式**\n\n输出一行一个整数，表示最高的契合度。\n\n**样例输入 #1**\n```\n3\n1 2 3\n```\n\n**样例输出 #1**\n```\n2\n```\n\n**样例输入 #2**\n```\n5\n5 6 2 10 13\n\n```\n\n**样例输出 #2**\n```\n8\n```\n\n**说明/提示**\n\n**样例解释 1**  \n\n可以编号为 $2,3$ 的食材之间的契合度为 $2\\ \\text{and} \\ 3=2$，是所有食材两两之间最高的契合度。\n\n**样例解释 2** \n\n可以编号为 $3,4$ 的食材之间的契合度为 $10\\ \\text{and}\\ 13=8$，是所有食材两两之间最高的契合度。\n\n**数据范围**\n\n对于 $40\\%$ 的测试点，保证 $N \\le 1,000$；\n\n对于所有测试点，保证 $N \\le 10^6$，$0\\le a_i \\le 2,147,483,647$。",
      "options": [],
      "section": "GESP 编程操作题"
    }
  ]
}